MyPackage/__init__.py
MyPackage/main.py
My_little_test_here-1.0.dist-info/METADATA
My_little_test_here-1.0.dist-info/WHEEL
My_little_test_here-1.0.dist-info/top_level.txt
My_little_test_here-1.0.dist-info/RECORD
